LICENSE
MANIFEST.in
README.md
setup.py
crysnet/__init__.py
crysnet.egg-info/PKG-INFO
crysnet.egg-info/SOURCES.txt
crysnet.egg-info/dependency_links.txt
crysnet.egg-info/requires.txt
crysnet.egg-info/top_level.txt
crysnet/activations/__init__.py
crysnet/activations/activations.py
crysnet/callbacks/__init__.py
crysnet/callbacks/cosineannealing.py
crysnet/data/__init__.py
crysnet/data/crystalgraph.py
crysnet/data/database.py
crysnet/data/embedding.py
crysnet/data/generator.py
crysnet/data/mendeleev.json
crysnet/layers/__init__.py
crysnet/layers/crystalgraphlayer.py
crysnet/layers/edgenetworklayer.py
crysnet/layers/graphnetworklayer.py
crysnet/layers/graphtransformer.py
crysnet/layers/mpnntransformer.py
crysnet/layers/partitionpaddinglayer.py
crysnet/layers/readout.py
crysnet/models/GraphModel_MpnnTransformer.py
crysnet/models/__init__.py
crysnet/models/gnnmodel.py
crysnet/models/graphmodel.py
crysnet/models/model/band_gap.hdf5
crysnet/models/model/formation_energy.hdf5
crysnet/models/model/metal.hdf5
crysnet/models/model/topology_multi.hdf5
crysnet/utils/__init__.py
crysnet/utils/get_nn.py
crysnet/utils/spherical_harmonics.py
crysnet/utils/tensor.py
crysnet/utils/utils.py